{
    "url": [
        {
            "nom": "123rf",
            "url": "fr.123rf.com",
            "extension": "2",
            "type": "Licite"
        },
        {
            "nom": "6play",
            "url": "www.6play.fr",
            "extension": "2",
            "type": "Licite"
        },
        {
            "nom": "7 Digital",
            "url": "fr.7digital.com",
            "extension": "2",
            "type": "Licite"
        },
        {
            "nom": "7switch",
            "url": "www.7switch.com/fr",
            "extension": "2",
            "type": "Licite"
        },
        {
            "nom": "AB1",
            "url": "www.ab1.tv/Live-Replay",
            "extension": "2",
            "type": "Licite"
        },
        {
            "nom": "ABU : la bibliothèque universelle",
            "url": "abu.cnam.fr",
            "extension": "2",
            "type": "Licite"
        },
        {
            "nom": "Acast",
            "url": "www.acast.com",
            "extension": "2",
            "type": "Licite"
        },
        {
            "nom": "Actes sud",
            "url": "numerique.librairieactessud.com",
            "extension": "2",
            "type": "Licite"
        },
        {
            "nom": "Action",
            "url": "www.actiontv.fr",
            "extension": "2",
            "type": "Licite"
        },
        {
            "nom": "Action Max",
            "url": "BoxTv",
            "extension": "0",
            "type": "Licite"
        },
        {
            "nom": "ADN",
            "url": "www.animedigitalnetwork.fr",
            "extension": "1",
            "type": "Licite"
        },
        {
            "nom": "Adobe Stock",
            "url": "fr.fotolia.com",
            "extension": "2",
            "type": "Licite"
        },
        {
            "nom": "Aeria Games",
            "url": "www.aeriagames.com",
            "extension": "2",
            "type": "Licite"
        },
        {
            "nom": "Alexandrie online",
            "url": "www.alexandrie.org",
            "extension": "2",
            "type": "Licite"
        },
        {
            "nom": "Allskreen",
            "url": "www.allskreen.fr",
            "extension": "1",
            "type": "Licite"
        },
        {
            "nom": "Amazon (livre numérique)",
            "url": "www.amazon.fr/ebooks-kindle",
            "extension": "2",
            "type": "Licite"
        },
        {
            "nom": "Amazon music",
            "url": "www.amazon.fr/telecharger-musique-mp3-amazon-music/b?ie=UTF8&node=77196031",
            "extension": "2",
            "type": "Licite"
        },
        {
            "nom": "Amazon music unlimited",
            "url": "www.amazon.com/gp/dmusic/promotions/AmazonMusicUnlimited",
            "extension": "2",
            "type": "Licite"
        },
        {
            "nom": "Amazon prime music",
            "url": "www.amazon.fr/music/prime",
            "extension": "2",
            "type": "Licite"
        },
        {
            "nom": "Amazon prime reading",
            "url": "www.amazon.fr/kindle-dbs/fd/nonprime-pr",
            "extension": "2",
            "type": "Licite"
        },
        {
            "nom": "Amazon prime vidéo",
            "url": "www.primevideo.com/?_encoding=UTF8&sr=1",
            "extension": "2",
            "type": "Licite"
        },
        {
            "nom": "Animaux TV",
            "url": "www.animauxtv.fr/Default.aspx",
            "extension": "3",
            "type": "Licite"
        },
        {
            "nom": "Antstream",
            "url": "www.antstream.com",
            "extension": "2",
            "type": "Licite"
        },
        {
            "nom": "Apple Arcade",
            "url": "www.apple.com/fr/apple-arcade",
            "extension": "2",
            "type": "Licite"
        },
        {
            "nom": "Apple iBooks",
            "url": "itunes.apple.com/fr/genre/books/id38 ",
            "extension": "2",
            "type": "Licite"
        },
        {
            "nom": "Apple music",
            "url": "www.apple.com/fr/music",
            "extension": "2",
            "type": "Licite"
        },
        {
            "nom": "Apple podcast",
            "url": "Application",
            "extension": "0",
            "type": "Licite"
        },
        {
            "nom": "AppleTV+",
            "url": "tv.apple.com",
            "extension": "2",
            "type": "Licite"
        },
        {
            "nom": "Art Book Magazine",
            "url": "www.artbookmagazine.com",
            "extension": "2",
            "type": "Licite"
        },
        {
            "nom": "Arte boutique",
            "url": "boutique.arte.tv/homepage.html",
            "extension": "3",
            "type": "Licite"
        },
        {
            "nom": "Arte concert",
            "url": "www.arte.tv/fr/arte-concert",
            "extension": "2",
            "type": "Licite"
        },
        {
            "nom": "Arte Radio",
            "url": "www.arteradio.com",
            "extension": "2",
            "type": "Licite"
        },
        {
            "nom": "Arte TV",
            "url": "www.arte.tv/fr",
            "extension": "2",
            "type": "Licite"
        },
        {
            "nom": "Athenaeum",
            "url": "ebook.athenaeum.com",
            "extension": "2",
            "type": "Licite"
        },
        {
            "nom": "Atramenta",
            "url": "www.atramenta.net",
            "extension": "2",
            "type": "Licite"
        },
        {
            "nom": "Audible",
            "url": "www.audible.fr",
            "extension": "2",
            "type": "Licite"
        },
        {
            "nom": "Audio Now",
            "url": "www.audionow.fr",
            "extension": "1",
            "type": "Licite"
        },
        {
            "nom": "Audiolib",
            "url": "www.audiolib.fr",
            "extension": "2",
            "type": "Licite"
        },
        {
            "nom": "AutoMoto La Chaîne",
            "url": "www.automoto-lachaine.fr",
            "extension": "2",
            "type": "Licite"
        },
        {
            "nom": "Bandai Namco Ent",
            "url": "www.bandainamcoent.fun/fr",
            "extension": "2",
            "type": "Licite"
        },
        {
            "nom": "Bandcamp",
            "url": "www.bandcamp.com",
            "extension": "1",
            "type": "Licite"
        },
        {
            "nom": "Bayday",
            "url": "www.bayday.com",
            "extension": "2",
            "type": "Licite"
        },
        {
            "nom": "BBC World news",
            "url": "www.bbc.co.uk/news/world",
            "extension": "3",
            "type": "Licite"
        },
        {
            "nom": "Bbox VOD",
            "url": "IPTV",
            "extension": "0",
            "type": "Licite"
        },
        {
            "nom": "Bdbuzz",
            "url": "www.bdbuzz.net",
            "extension": "2",
            "type": "Licite"
        },
        {
            "nom": "Beatport",
            "url": "www.beatport.com",
            "extension": "2",
            "type": "Licite"
        },
        {
            "nom": "BeINSport",
            "url": "www.beinsports.fr",
            "extension": "2",
            "type": "Licite"
        },
        {
            "nom": "Benshi ",
            "url": "www.benshi.fr",
            "extension": "1",
            "type": "Licite"
        },
        {
            "nom": "BFM Business",
            "url": "bfmbusiness.bfmtv.com",
            "extension": "2",
            "type": "Licite"
        },
        {
            "nom": "BFMTV",
            "url": "www.bfmtv.com",
            "extension": "2",
            "type": "Licite"
        },
        {
            "nom": "Biblio Manuels",
            "url": "www.manuelnumerique.com",
            "extension": "2",
            "type": "Licite"
        },
        {
            "nom": "Bibliothèque de la finance",
            "url": "bibliotheque.revue-banque.fr",
            "extension": "2",
            "type": "Licite"
        },
        {
            "nom": "Bibliothèque de Paris",
            "url": "bibliotheque-numerique.paris.fr",
            "extension": "2",
            "type": "Licite"
        },
        {
            "nom": "Bibliothèque numérique romande ",
            "url": "www.ebooks-bnr.com",
            "extension": "2",
            "type": "Licite"
        },
        {
            "nom": "Bibliothèque numérique territoriale",
            "url": "bnt.execvox.com",
            "extension": "2",
            "type": "Licite"
        },
        {
            "nom": "Bibliothèque réseau francophone numérique",
            "url": "www.rfnum-bibliotheque.or",
            "extension": "1",
            "type": "Licite"
        },
        {
            "nom": "Bibliothèque russe et slave",
            "url": "bibliotheque-russe-et-slave.com/index1.html",
            "extension": "2",
            "type": "Licite"
        },
        {
            "nom": "Bibliovox",
            "url": "www.bibliovox.com",
            "extension": "2",
            "type": "Licite"
        },
        {
            "nom": "Big Fish",
            "url": "www.bigfishgames.fr",
            "extension": "2",
            "type": "Licite"
        },
        {
            "nom": "Bigstock",
            "url": "www.bigstockphoto.com/fr",
            "extension": "2",
            "type": "Licite"
        },
        {
            "nom": "Binge",
            "url": "www.binge.audio",
            "extension": "2",
            "type": "Licite"
        },
        {
            "nom": "Biosphoto",
            "url": "www.biosphoto.com",
            "extension": "2",
            "type": "Licite"
        },
        {
            "nom": "Blackberry",
            "url": "appworld.blackberry.com/webstore/?",
            "extension": "2",
            "type": "Licite"
        },
        {
            "nom": "Blizzard",
            "url": "www.blizzard.com",
            "extension": "2",
            "type": "Licite"
        },
        {
            "nom": "Boing",
            "url": "www.boingtv.fr",
            "extension": "2",
            "type": "Licite"
        },
        {
            "nom": "Book d'oreille",
            "url": "www.bookdoreille.com/fr",
            "extension": "1",
            "type": "Licite"
        },
        {
            "nom": "Bookeen",
            "url": "www.bookeenstore.com",
            "extension": "2",
            "type": "Licite"
        },
        {
            "nom": "Bookland",
            "url": "www.bookland.com/fra",
            "extension": "1",
            "type": "Licite"
        },
        {
            "nom": "Boomerang",
            "url": "www.boomerangtv.fr",
            "extension": "2",
            "type": "Licite"
        },
        {
            "nom": "Booska-P",
            "url": "www.booska-p.com",
            "extension": "2",
            "type": "Licite"
        },
        {
            "nom": "Bordas",
            "url": "www.editions-bordas.fr",
            "extension": "2",
            "type": "Licite"
        },
        {
            "nom": "Bouquineo",
            "url": "www.bouquineo.fr",
            "extension": "2",
            "type": "Licite"
        },
        {
            "nom": "Bref Cinéma",
            "url": "www.brefcinema.com",
            "extension": "2",
            "type": "Licite"
        },
        {
            "nom": "Brouillon de culture",
            "url": "livresnumeriques.brouillondeculture.fr",
            "extension": "2",
            "type": "Licite"
        },
        {
            "nom": "Bynwr",
            "url": "www.bynwr.com",
            "extension": "2",
            "type": "Licite"
        },
        {
            "nom": "Cairn",
            "url": "www.cairn.info",
            "extension": "2",
            "type": "Licite"
        },
        {
            "nom": "Canal VOD",
            "url": "vod.canalplus.com",
            "extension": "2",
            "type": "Licite"
        },
        {
            "nom": "Canal+ Formula 1",
            "url": "MyCanal",
            "extension": "0",
            "type": "Licite"
        },
        {
            "nom": "Canal+ series",
            "url": "www.mycanal.fr/series",
            "extension": "2",
            "type": "Licite"
        },
        {
            "nom": "Canstockphoto",
            "url": "www.canstockphoto.fr",
            "extension": "2",
            "type": "Licite"
        },
        {
            "nom": "Castbox",
            "url": "www.castbox.fm",
            "extension": "1",
            "type": "Licite"
        },
        {
            "nom": "Chapitre.com",
            "url": "ebook.chapitre.com",
            "extension": "2",
            "type": "Licite"
        },
        {
            "nom": "Chasse et pêche",
            "url": "www.chasseetpechetv.fr/Default.aspx",
            "extension": "3",
            "type": "Licite"
        },
        {
            "nom": "Chérie 25",
            "url": "www.cherie25.fr",
            "extension": "1",
            "type": "Licite"
        },
        {
            "nom": "Chérie FM",
            "url": "www.cheriefm.fr",
            "extension": "2",
            "type": "Licite"
        },
        {
            "nom": "Chine ancienne",
            "url": "www.chineancienne.fr",
            "extension": "2",
            "type": "Licite"
        },
        {
            "nom": "Ciné VR",
            "url": "www.cinevr.io",
            "extension": "1",
            "type": "Licite"
        },
        {
            "nom": "Ciné-archives",
            "url": "www.cinearchives.org",
            "extension": "2",
            "type": "Licite"
        },
        {
            "nom": "Cinéma(s) à la demande",
            "url": "www.cinemasalademande.com",
            "extension": "2",
            "type": "Licite"
        },
        {
            "nom": "Citebd",
            "url": "librairie.citebd.org",
            "extension": "2",
            "type": "Licite"
        },
        {
            "nom": "Cnews",
            "url": "www.cnews.fr",
            "extension": "2",
            "type": "Licite"
        },
        {
            "nom": "CNN",
            "url": "edition.cnn.com",
            "extension": "2",
            "type": "Licite"
        },
        {
            "nom": "Collection RVB",
            "url": "www.collectionrvb.com",
            "extension": "1",
            "type": "Licite"
        },
        {
            "nom": "Comixology",
            "url": "www.comixology.fr",
            "extension": "2",
            "type": "Licite"
        },
        {
            "nom": "Crime district",
            "url": "www.crimedistrict.tv",
            "extension": "2",
            "type": "Licite"
        },
        {
            "nom": "Crunchyroll",
            "url": "www.crunchyroll.com",
            "extension": "2",
            "type": "Licite"
        },
        {
            "nom": "Cultura",
            "url": "www.cultura.com/e-books/e-books.html",
            "extension": "3",
            "type": "Licite"
        },
        {
            "nom": "Culture TV5 Monde",
            "url": "culture.tv5monde.com",
            "extension": "2",
            "type": "Licite"
        },
        {
            "nom": "Culturebox",
            "url": "culturebox.francetvinfo.fr",
            "extension": "2",
            "type": "Licite"
        },
        {
            "nom": "Decitre",
            "url": "www.decitre.fr/ebook.html",
            "extension": "3",
            "type": "Licite"
        },
        {
            "nom": "Deezer",
            "url": "www.deezer.fr",
            "extension": "2",
            "type": "Licite"
        },
        {
            "nom": "Delitoon",
            "url": "www.delitoon.com",
            "extension": "2",
            "type": "Licite"
        },
        {
            "nom": "Demain !",
            "url": "www.demain.fr",
            "extension": "2",
            "type": "Licite"
        },
        {
            "nom": "Depositphotos",
            "url": "fr.depositphotos.com",
            "extension": "2",
            "type": "Licite"
        },
        {
            "nom": "Deviantart",
            "url": "www.deviantart.com",
            "extension": "2",
            "type": "Licite"
        },
        {
            "nom": "Digibidi",
            "url": "www.digibidi.com",
            "extension": "2",
            "type": "Licite"
        },
        {
            "nom": "Discovery VR",
            "url": "www.realite-virtuelle.com/partez-decouverte-monde-discovery-vr",
            "extension": "2",
            "type": "Licite"
        },
        {
            "nom": "Disney+",
            "url": "www.disneyplus.com",
            "extension": "2",
            "type": "Licite"
        },
        {
            "nom": "DLGamer",
            "url": "www.dlgamer.fr",
            "extension": "2",
            "type": "Licite"
        },
        {
            "nom": "Dramapassion",
            "url": "www.dramapassion.com",
            "extension": "2",
            "type": "Licite"
        },
        {
            "nom": "Dreamstime",
            "url": "fr.dreamstime.com",
            "extension": "2",
            "type": "Licite"
        },
        {
            "nom": "Dunod",
            "url": "www.dunod.com",
            "extension": "2",
            "type": "Licite"
        },
        {
            "nom": "EA Play",
            "url": "www.ea.com/fr-fr/ea-play/news/welcome-to-ea-play",
            "extension": "2",
            "type": "Licite"
        },
        {
            "nom": "Ebook du livre de poche",
            "url": "numerique.livredepoche.com",
            "extension": "2",
            "type": "Licite"
        },
        {
            "nom": "eboxeditions",
            "url": "www.eboxeditions.com",
            "extension": "2",
            "type": "Licite"
        },
        {
            "nom": "Ecinema",
            "url": "www.e-cinema.com",
            "extension": "2",
            "type": "Licite"
        },
        {
            "nom": "Edilivre",
            "url": "www.edilivre.com/librairie.html",
            "extension": "3",
            "type": "Licite"
        },
        {
            "nom": "Editions Eni",
            "url": "www.editions-eni.fr",
            "extension": "2",
            "type": "Licite"
        },
        {
            "nom": "Editions Harlequin",
            "url": "www.harlequin.fr",
            "extension": "2",
            "type": "Licite"
        },
        {
            "nom": "Editions Hatier",
            "url": "www.editions-hatier.fr/offre-numerique",
            "extension": "2",
            "type": "Licite"
        },
        {
            "nom": "Editions Larcier",
            "url": "www.larciergroup.com/fr",
            "extension": "2",
            "type": "Licite"
        },
        {
            "nom": "Editions Retz",
            "url": "www.editions-retz.com/numerique",
            "extension": "2",
            "type": "Licite"
        },
        {
            "nom": "Editions Sciences Humaines",
            "url": "editions.scienceshumaines.com",
            "extension": "2",
            "type": "Licite"
        },
        {
            "nom": "Eeko Podcast",
            "url": "www.eeko-podcast.fr",
            "extension": "2",
            "type": "Licite"
        },
        {
            "nom": "Efélé",
            "url": "www.efele.net/ebooks",
            "extension": "1",
            "type": "Licite"
        },
        {
            "nom": "E-librairie Leclerc",
            "url": "e-librairie.e-leclerc.com",
            "extension": "2",
            "type": "Licite"
        },
        {
            "nom": "Elsevier Masson",
            "url": "www.elsevier-masson.fr",
            "extension": "2",
            "type": "Licite"
        },
        {
            "nom": "Elson",
            "url": "www.elson.fr",
            "extension": "2",
            "type": "Licite"
        },
        {
            "nom": "Emaginaire",
            "url": "www.emaginaire.com",
            "extension": "2",
            "type": "Licite"
        },
        {
            "nom": "Emusic",
            "url": "www.emusic.com",
            "extension": "2",
            "type": "Licite"
        },
        {
            "nom": "Eole",
            "url": "eole.avh.asso.fr",
            "extension": "3",
            "type": "Licite"
        },
        {
            "nom": "ePagine",
            "url": "www.epagine.fr",
            "extension": "2",
            "type": "Licite"
        },
        {
            "nom": "EpicGames",
            "url": "www.epicgames.com",
            "extension": "2",
            "type": "Licite"
        },
        {
            "nom": "Epresse.fr",
            "url": "www.epresse.fr",
            "extension": "2",
            "type": "Licite"
        },
        {
            "nom": "Ernster",
            "url": "ernster.numilog.com",
            "extension": "2",
            "type": "Licite"
        },
        {
            "nom": "Esperluete",
            "url": "www.esperluete.fr",
            "extension": "2",
            "type": "Licite"
        },
        {
            "nom": "Euronews",
            "url": "fr.euronews.com",
            "extension": "2",
            "type": "Licite"
        },
        {
            "nom": "European Film Factory",
            "url": "www.europeanfilmfactory.eu",
            "extension": "2",
            "type": "Licite"
        },
        {
            "nom": "Europeana",
            "url": "www.europeana.eu",
            "extension": "2",
            "type": "Licite"
        },
        {
            "nom": "Eurosport player",
            "url": "www.eurosportplayer.fr",
            "extension": "2",
            "type": "Licite"
        },
        {
            "nom": "Feedbooks",
            "url": "fr.feedbooks.com",
            "extension": "2",
            "type": "Licite"
        },
        {
            "nom": "Filmdoo",
            "url": "www.filmdoo.com",
            "extension": "2",
            "type": "Licite"
        },
        {
            "nom": "FilmoTV",
            "url": "www.filmotv.fr",
            "extension": "2",
            "type": "Licite"
        },
        {
            "nom": "Films pour enfants",
            "url": "www.films-pour-enfants.com",
            "extension": "2",
            "type": "Licite"
        },
        {
            "nom": "FilmsDocumentaires.com",
            "url": "www.filmsdocumentaires.com",
            "extension": "2",
            "type": "Licite"
        },
        {
            "nom": "FIP",
            "url": "www.fip.fr",
            "extension": "2",
            "type": "Licite"
        },
        {
            "nom": "Fnac",
            "url": "www.fnac.com/telecharger-ebook.asp",
            "extension": "3",
            "type": "Licite"
        },
        {
            "nom": "Foxplay",
            "url": "Canal",
            "extension": "0",
            "type": "Licite"
        },
        {
            "nom": "France 24",
            "url": "www.france24.com/fr",
            "extension": "2",
            "type": "Licite"
        },
        {
            "nom": "France loisirs",
            "url": "www.franceloisirs.com/catalogue/rubrique/EBOOKS/eBooks",
            "extension": "2",
            "type": "Licite"
        },
        {
            "nom": "France musique",
            "url": "www.francemusique.fr",
            "extension": "2",
            "type": "Licite"
        },
        {
            "nom": "France TV",
            "url": "www.france.tv",
            "extension": "2",
            "type": "Licite"
        },
        {
            "nom": "Funradio",
            "url": "www.funradio.fr",
            "extension": "2",
            "type": "Licite"
        },
        {
            "nom": "Furet du nord",
            "url": "ebook.furet.com",
            "extension": "2",
            "type": "Licite"
        },
        {
            "nom": "Fuze Forge",
            "url": "store.fuzeforge.com",
            "extension": "2",
            "type": "Licite"
        },
        {
            "nom": "Gallica",
            "url": "gallica.bnf.fr",
            "extension": "2",
            "type": "Licite"
        },
        {
            "nom": "Game One",
            "url": "www.gameone.net",
            "extension": "2",
            "type": "Licite"
        },
        {
            "nom": "Gameasy",
            "url": "www.gameasy.com/fr",
            "extension": "2",
            "type": "Licite"
        },
        {
            "nom": "Gamesplanet",
            "url": "fr.gamesplanet.com",
            "extension": "2",
            "type": "Licite"
        },
        {
            "nom": "Géo Télévision",
            "url": "Amazon Prime",
            "extension": "0",
            "type": "Licite"
        },
        {
            "nom": "Gibert joseph",
            "url": "gibertjoseph.epagine.fr",
            "extension": "2",
            "type": "Licite"
        },
        {
            "nom": "Gog.com",
            "url": "www.gog.com",
            "extension": "2",
            "type": "Licite"
        },
        {
            "nom": "Golfchannel",
            "url": "www.golfchannel.fr",
            "extension": "2",
            "type": "Licite"
        },
        {
            "nom": "Google Chrome Web Store",
            "url": "chrome.google.com/webstore/category/app/3-games",
            "extension": "2",
            "type": "Licite"
        },
        {
            "nom": "Google Play",
            "url": "play.google.com/store",
            "extension": "2",
            "type": "Licite"
        },
        {
            "nom": "Google Podcast",
            "url": "podcasts.google.com",
            "extension": "2",
            "type": "Licite"
        },
        {
            "nom": "Gulli",
            "url": "svod.gulli.fr",
            "extension": "2",
            "type": "Licite"
        },
        {
            "nom": "Gulli Replay",
            "url": "replay.gulli.fr",
            "extension": "2",
            "type": "Licite"
        },
        {
            "nom": "Hachette.fr",
            "url": "www.hachette.fr/e-books/tous",
            "extension": "2",
            "type": "Licite"
        },
        {
            "nom": "Hardigan",
            "url": "www.hardigan.fr",
            "extension": "1",
            "type": "Licite"
        },
        {
            "nom": "Harmattan TV",
            "url": "www.harmattantv.com",
            "extension": "2",
            "type": "Licite"
        },
        {
            "nom": "Henri",
            "url": "www.cinematheque.fr/henri",
            "extension": "2",
            "type": "Licite"
        },
        {
            "nom": "Highresaudio",
            "url": "www.highresaudio.com/en",
            "extension": "2",
            "type": "Licite"
        },
        {
            "nom": "Histoire",
            "url": "www.histoire.fr",
            "extension": "2",
            "type": "Licite"
        },
        {
            "nom": "Hopster",
            "url": "Application",
            "extension": "0",
            "type": "Licite"
        },
        {
            "nom": "Hotmix Radio",
            "url": "www.hotmixradio.fr",
            "extension": "2",
            "type": "Licite"
        },
        {
            "nom": "Humano",
            "url": "www.humano.com/digital",
            "extension": "2",
            "type": "Licite"
        },
        {
            "nom": "iBibliothèque",
            "url": "www.ibibliotheque.fr",
            "extension": "2",
            "type": "Licite"
        },
        {
            "nom": "I-concerts",
            "url": "iconcerts.stingray.com/fr/US",
            "extension": "2",
            "type": "Licite"
        },
        {
            "nom": "Idagio",
            "url": "www.idagio.com",
            "extension": "2",
            "type": "Licite"
        },
        {
            "nom": "Imago",
            "url": "www.imagotv.fr",
            "extension": "2",
            "type": "Licite"
        },
        {
            "nom": "Infinikids",
            "url": "www.infinikids.fr",
            "extension": "2",
            "type": "Licite"
        },
        {
            "nom": "Inlibroveritas",
            "url": "www.inlibroveritas.net",
            "extension": "2",
            "type": "Licite"
        },
        {
            "nom": "IS ebooks",
            "url": "www.is-ebooks.com",
            "extension": "2",
            "type": "Licite"
        },
        {
            "nom": "istockphoto",
            "url": "francais.istockphoto.com",
            "extension": "2",
            "type": "Licite"
        },
        {
            "nom": "iTunes",
            "url": "www.apple.com/fr/itunes",
            "extension": "2",
            "type": "Licite"
        },
        {
            "nom": "IziBook Eyrolles",
            "url": "izibook.eyrolles.com",
            "extension": "2",
            "type": "Licite"
        },
        {
            "nom": "Izneo",
            "url": "www.izneo.com/fr",
            "extension": "2",
            "type": "Licite"
        },
        {
            "nom": "J'ai lu (pour elle)",
            "url": "www.jailupourelle.com/ebook.html",
            "extension": "3",
            "type": "Licite"
        },
        {
            "nom": "J'aime Lire Store",
            "url": "www.boutique-jaimelirestore.com",
            "extension": "1",
            "type": "Licite"
        },
        {
            "nom": "Jamendo",
            "url": "www.jamendo.com/fr",
            "extension": "2",
            "type": "Licite"
        },
        {
            "nom": "JauntVR",
            "url": "Application",
            "extension": "0",
            "type": "Licite"
        },
        {
            "nom": "Jazz Radio",
            "url": "www.jazzradio.fr",
            "extension": "2",
            "type": "Licite"
        },
        {
            "nom": "Je publie",
            "url": "www.jepublie.com/vos-publications.aspx",
            "extension": "3",
            "type": "Licite"
        },
        {
            "nom": "Junodownload",
            "url": "www.junodownload.com",
            "extension": "2",
            "type": "Licite"
        },
        {
            "nom": "Kidzinmind",
            "url": "www.kidzinmind.com/fr",
            "extension": "2",
            "type": "Licite"
        },
        {
            "nom": "kinoscript",
            "url": "www.stvpress.com",
            "extension": "1",
            "type": "Licite"
        },
        {
            "nom": "Kobo",
            "url": "www.kobobooks.fr",
            "extension": "2",
            "type": "Licite"
        },
        {
            "nom": "Kongregate",
            "url": "www.kongregate.com",
            "extension": "2",
            "type": "Licite"
        },
        {
            "nom": "KTO",
            "url": "www.ktotv.com",
            "extension": "2",
            "type": "Licite"
        },
        {
            "nom": "Kwafilms",
            "url": "www.kwafilms.com",
            "extension": "2",
            "type": "Licite"
        },
        {
            "nom": "La bibliothèque d'ebooks",
            "url": "www.bibebook.com",
            "extension": "2",
            "type": "Licite"
        },
        {
            "nom": "La galerne librairie",
            "url": "www.lagalerne.com/boutique/36/ebooks-livres-numeriques-electroniques",
            "extension": "2",
            "type": "Licite"
        },
        {
            "nom": "La Toile",
            "url": "www.la-toile-vod.com",
            "extension": "1",
            "type": "Licite"
        },
        {
            "nom": "LaCinetek",
            "url": "www.lacinetek.com/fr",
            "extension": "1",
            "type": "Licite"
        },
        {
            "nom": "La librairie RH",
            "url": "www.la-librairie-rh.com",
            "extension": "2",
            "type": "Licite"
        },
        {
            "nom": "L'alinéa",
            "url": "livre-numerique.librairielalinea.fr",
            "extension": "2",
            "type": "Licite"
        },
        {
            "nom": "Lamartine",
            "url": "numerique.lamartine.fr",
            "extension": "2",
            "type": "Licite"
        },
        {
            "nom": "L'ange bleu",
            "url": "numerique.librairielangebleu.com",
            "extension": "2",
            "type": "Licite"
        },
        {
            "nom": "L'appel du livre",
            "url": "numerique.appeldulivre.fr",
            "extension": "2",
            "type": "Licite"
        },
        {
            "nom": "L'arbre à lettres",
            "url": "www.arbrealettres.com",
            "extension": "2",
            "type": "Licite"
        },
        {
            "nom": "L'armitière",
            "url": "www.armitiere.com",
            "extension": "2",
            "type": "Licite"
        },
        {
            "nom": "Lavoisier",
            "url": "e.lavoisier.fr",
            "extension": "2",
            "type": "Licite"
        },
        {
            "nom": "LCI",
            "url": "www.lci.fr",
            "extension": "1",
            "type": "Licite"
        },
        {
            "nom": "LCP AN",
            "url": "www.lcp.fr",
            "extension": "2",
            "type": "Licite"
        },
        {
            "nom": "Le Bélial",
            "url": "www.belial.fr",
            "extension": "2",
            "type": "Licite"
        },
        {
            "nom": "Le Poste Général",
            "url": "www.lepostegeneral.fr",
            "extension": "1",
            "type": "Licite"
        },
        {
            "nom": "Le serpent qui danse",
            "url": "www.leserpentquidanse.com",
            "extension": "2",
            "type": "Licite"
        },
        {
            "nom": "Lecteurs.com",
            "url": "www.lecteurs.com/ebooks",
            "extension": "2",
            "type": "Licite"
        },
        {
            "nom": "Lekiosk",
            "url": "get.lekiosk.com/applications-lekiosk",
            "extension": "2",
            "type": "Licite"
        },
        {
            "nom": "L'équipe 21",
            "url": "www.lequipe21.fr",
            "extension": "2",
            "type": "Licite"
        },
        {
            "nom": "Les beaux titres",
            "url": "ebook.lesbeauxtitres.com",
            "extension": "2",
            "type": "Licite"
        },
        {
            "nom": "Les éditions Amalthée",
            "url": "www.editions-amalthee.com/edition-livre-genre/ebooks",
            "extension": "2",
            "type": "Licite"
        },
        {
            "nom": "Les éditions Blanche de Peuterey",
            "url": "www.peuterey-editions.com",
            "extension": "2",
            "type": "Licite"
        },
        {
            "nom": "Les éditions du Net",
            "url": "www.leseditionsdunet.com/index.php",
            "extension": "3",
            "type": "Licite"
        },
        {
            "nom": "Les éditions persée",
            "url": "www.editions-persee.fr",
            "extension": "2",
            "type": "Licite"
        },
        {
            "nom": "Les libraires",
            "url": "www.leslibraires.fr/dossiers/livres-numeriques",
            "extension": "2",
            "type": "Licite"
        },
        {
            "nom": "Libération Ebook ",
            "url": "www.liberation.fr/bibliotheque",
            "extension": "2",
            "type": "Licite"
        },
        {
            "nom": "Librairie Antillaise",
            "url": "librairieantillaise.epagine.fr",
            "extension": "2",
            "type": "Licite"
        },
        {
            "nom": "Librairie attitude",
            "url": "livresnumeriques.librairie-attitude.com",
            "extension": "2",
            "type": "Licite"
        },
        {
            "nom": "Librairie Autrement",
            "url": "numerique.sa-autrement.com",
            "extension": "2",
            "type": "Licite"
        },
        {
            "nom": "Librairie cheminant",
            "url": "www.monlibrairenumerique.com",
            "extension": "2",
            "type": "Licite"
        },
        {
            "nom": "Librairie contact",
            "url": "numerique.librairiecontact.fr",
            "extension": "2",
            "type": "Licite"
        },
        {
            "nom": "Librairie de paris saint-etienne",
            "url": "numerique.librairiedeparis.fr",
            "extension": "2",
            "type": "Licite"
        },
        {
            "nom": "Librairie delamain",
            "url": "www.malibrairienumerique.com/ ",
            "extension": "2",
            "type": "Licite"
        },
        {
            "nom": "Librairie des lois",
            "url": "librairiedeslois.numilog.com",
            "extension": "2",
            "type": "Licite"
        },
        {
            "nom": "Librairie Dialogues",
            "url": "www.librairiedialogues.fr/boutique/3/ebooks-livres-numeriques-electroniques",
            "extension": "2",
            "type": "Licite"
        },
        {
            "nom": "Librairie durance",
            "url": "ebook.librairiedurance.fr",
            "extension": "2",
            "type": "Licite"
        },
        {
            "nom": "Librairie filigranes",
            "url": "filigranes.epagine.fr",
            "extension": "2",
            "type": "Licite"
        },
        {
            "nom": "Librairie Galignani",
            "url": "ebook.galignani.fr",
            "extension": "2",
            "type": "Licite"
        },
        {
            "nom": "Librairie Gallimard",
            "url": "www.gallimardnumerique.com",
            "extension": "2",
            "type": "Licite"
        },
        {
            "nom": "Librairie Kleber",
            "url": "numerique.librairie-kleber.com",
            "extension": "2",
            "type": "Licite"
        },
        {
            "nom": "Librairie le divan",
            "url": "www.leslivresnumeriques.com",
            "extension": "2",
            "type": "Licite"
        },
        {
            "nom": "Librairie le failler",
            "url": "www.librairielefailler.fr/selec-5368/livres-numeriques",
            "extension": "2",
            "type": "Licite"
        },
        {
            "nom": "Librairie Le passage alençon",
            "url": "lepassage.epagine.fr",
            "extension": "2",
            "type": "Licite"
        },
        {
            "nom": "Librairie Martin-Delbert",
            "url": "ebook.martin-delbert.fr",
            "extension": "2",
            "type": "Licite"
        },
        {
            "nom": "Librairie Massena",
            "url": "numerique.librairiemassena.com",
            "extension": "2",
            "type": "Licite"
        },
        {
            "nom": "Librairie Mollat",
            "url": "numerique.mollat.com",
            "extension": "2",
            "type": "Licite"
        },
        {
            "nom": "Librairie Montbarbon",
            "url": "montbarbon.tea-ebook.com",
            "extension": "2",
            "type": "Licite"
        },
        {
            "nom": "Librairie nantes numérique",
            "url": "www.librairie-nantes-numerique.fr",
            "extension": "2",
            "type": "Licite"
        },
        {
            "nom": "Librairie polar",
            "url": "librairie-polar.numilog.com",
            "extension": "2",
            "type": "Licite"
        },
        {
            "nom": "Librairie ryst",
            "url": "www.librairie-ryst.fr",
            "extension": "2",
            "type": "Licite"
        },
        {
            "nom": "Librairie torcatis",
            "url": "ebook.librairietorcatis.com",
            "extension": "2",
            "type": "Licite"
        },
        {
            "nom": "Librairies de paris",
            "url": "www.lalibrairienumerique.fr",
            "extension": "2",
            "type": "Licite"
        },
        {
            "nom": "Librel",
            "url": "www.librel.be",
            "extension": "2",
            "type": "Licite"
        },
        {
            "nom": "Librinova",
            "url": "www.librinova.com/librairie",
            "extension": "2",
            "type": "Licite"
        },
        {
            "nom": "Libthèque",
            "url": "www.libtheque.fr/index.php",
            "extension": "3",
            "type": "Licite"
        },
        {
            "nom": "Lisez !",
            "url": "www.lisez.com",
            "extension": "2",
            "type": "Licite"
        },
        {
            "nom": "litteratureaudio",
            "url": "www.litteratureaudio.com",
            "extension": "2",
            "type": "Licite"
        },
        {
            "nom": "Livrespourtous",
            "url": "www.livrespourtous.com",
            "extension": "2",
            "type": "Licite"
        },
        {
            "nom": "Lizzie",
            "url": "www.lizzie.audio",
            "extension": "2",
            "type": "Licite"
        },
        {
            "nom": "lovemyVOD",
            "url": "www.lovemyvod.fr",
            "extension": "2",
            "type": "Licite"
        },
        {
            "nom": "Lumni",
            "url": "cinema.lumni.fr/edutheque",
            "extension": "2",
            "type": "Licite"
        },
        {
            "nom": "Madelen INA",
            "url": "madelen.ina.fr",
            "extension": "2",
            "type": "Licite"
        },
        {
            "nom": "Maghreb VOD",
            "url": "IPTV",
            "extension": "0",
            "type": "Licite"
        },
        {
            "nom": "Maison du livre",
            "url": "numerique.maisondulivre.com",
            "extension": "2",
            "type": "Licite"
        },
        {
            "nom": "Mangadraft",
            "url": "www.mangadraft.com",
            "extension": "2",
            "type": "Licite"
        },
        {
            "nom": "Mangas",
            "url": "www.mangas.fr",
            "extension": "2",
            "type": "Licite"
        },
        {
            "nom": "Matton image",
            "url": "www.matton.fr",
            "extension": "2",
            "type": "Licite"
        },
        {
            "nom": "MCS VOD",
            "url": "Numericable",
            "extension": "0",
            "type": "Licite"
        },
        {
            "nom": "Medici.tv",
            "url": "www.medici.tv/fr",
            "extension": "2",
            "type": "Licite"
        },
        {
            "nom": "Melody.tv",
            "url": "www.melody.tv",
            "extension": "2",
            "type": "Licite"
        },
        {
            "nom": "Men's up TV",
            "url": "www.mensup.fr",
            "extension": "2",
            "type": "Licite"
        },
        {
            "nom": "Meslivresnumeriques",
            "url": "www.meslivresnumeriques.be",
            "extension": "2",
            "type": "Licite"
        },
        {
            "nom": "Mezzo",
            "url": "www.mezzo.tv/fr",
            "extension": "2",
            "type": "Licite"
        },
        {
            "nom": "MGM",
            "url": "Amazon Prime",
            "extension": "0",
            "type": "Licite"
        },
        {
            "nom": "Microsoft store",
            "url": "www.microsoft.com/fr-fr/store",
            "extension": "2",
            "type": "Licite"
        },
        {
            "nom": "Modern Score",
            "url": "www.modernscore.com",
            "extension": "2",
            "type": "Licite"
        },
        {
            "nom": "Molotov.tv",
            "url": "www.molotov.tv",
            "extension": "2",
            "type": "Licite"
        },
        {
            "nom": "Montagne TV",
            "url": "www.montagnetv.com",
            "extension": "2",
            "type": "Licite"
        },
        {
            "nom": "MTV",
            "url": "www.mtv.fr",
            "extension": "2",
            "type": "Licite"
        },
        {
            "nom": "Mubi",
            "url": "www.mubi.com/fr",
            "extension": "1",
            "type": "Licite"
        },
        {
            "nom": "Munki",
            "url": "pro.munki.audio",
            "extension": "2",
            "type": "Licite"
        },
        {
            "nom": "Museum",
            "url": "www.museumtv.fr",
            "extension": "1",
            "type": "Licite"
        },
        {
            "nom": "Musicme",
            "url": "www.musicme.com",
            "extension": "2",
            "type": "Licite"
        },
        {
            "nom": "Musopen",
            "url": "www.musopen.org/fr",
            "extension": "1",
            "type": "Licite"
        },
        {
            "nom": "Mycanal",
            "url": "www.mycanal.fr",
            "extension": "2",
            "type": "Licite"
        },
        {
            "nom": "Mycanal Kids",
            "url": "kids.mycanal.fr",
            "extension": "2",
            "type": "Licite"
        },
        {
            "nom": "MyTF1",
            "url": "www.tf1.fr",
            "extension": "2",
            "type": "Licite"
        },
        {
            "nom": "MyTF1VR",
            "url": "Application",
            "extension": "0",
            "type": "Licite"
        },
        {
            "nom": "myZen.tv",
            "url": "www.myzen.tv",
            "extension": "2",
            "type": "Licite"
        },
        {
            "nom": "Napster",
            "url": "fr.napster.com",
            "extension": "2",
            "type": "Licite"
        },
        {
            "nom": "Neobook",
            "url": "www.neobook.fr",
            "extension": "1",
            "type": "Licite"
        },
        {
            "nom": "Netflix",
            "url": "www.netflix.com/fr",
            "extension": "2",
            "type": "Licite"
        },
        {
            "nom": "Netflix VR",
            "url": "Application",
            "extension": "0",
            "type": "Licite"
        },
        {
            "nom": "Nintendo eShop",
            "url": "www.nintendo.fr/Divers/Nintendo-eShop/Nintendo-eShop-Nintendo-3DS-et-Wii-U-109605.html",
            "extension": "3",
            "type": "Licite"
        },
        {
            "nom": "Nokzedoc",
            "url": "www.nokzedoc.tv/home",
            "extension": "1",
            "type": "Licite"
        },
        {
            "nom": "NoMadMusic",
            "url": "www.nomadmusic.fr",
            "extension": "2",
            "type": "Licite"
        },
        {
            "nom": "Non stop people",
            "url": "www.non-stop-people.com",
            "extension": "2",
            "type": "Licite"
        },
        {
            "nom": "Nostalgie",
            "url": "www.nostalgie.fr",
            "extension": "2",
            "type": "Licite"
        },
        {
            "nom": "Noviscore",
            "url": "www.noviscore.fr",
            "extension": "2",
            "type": "Licite"
        },
        {
            "nom": "NRJ",
            "url": "www.nrj.fr",
            "extension": "2",
            "type": "Licite"
        },
        {
            "nom": "NRJ Play",
            "url": "www.nrj12.fr",
            "extension": "2",
            "type": "Licite"
        },
        {
            "nom": "Nugs.net",
            "url": "www.nugs.net",
            "extension": "2",
            "type": "Licite"
        },
        {
            "nom": "Numérique premium",
            "url": "www.numeriquepremium.com",
            "extension": "2",
            "type": "Licite"
        },
        {
            "nom": "Numilog",
            "url": "www.numilog.com",
            "extension": "2",
            "type": "Licite"
        },
        {
            "nom": "OCS",
            "url": "www.ocs.fr",
            "extension": "2",
            "type": "Licite"
        },
        {
            "nom": "OI Films",
            "url": "www.oi-film.com",
            "extension": "2",
            "type": "Licite"
        },
        {
            "nom": "Okidoki",
            "url": "www.okidoki-tv.com",
            "extension": "1",
            "type": "Licite"
        },
        {
            "nom": "Okoo",
            "url": "www.france.tv/okoo",
            "extension": "2",
            "type": "Licite"
        },
        {
            "nom": "OL Play",
            "url": "www.ol.fr/fr-fr/oltv/abonnement",
            "extension": "2",
            "type": "Licite"
        },
        {
            "nom": "OM Prime",
            "url": "www.om.fr/fr/om-prime",
            "extension": "2",
            "type": "Licite"
        },
        {
            "nom": "Onisep",
            "url": "librairie.onisep.fr",
            "extension": "2",
            "type": "Licite"
        },
        {
            "nom": "Open Culture",
            "url": "www.openculture.com",
            "extension": "2",
            "type": "Licite"
        },
        {
            "nom": "Open editions books",
            "url": "books.openedition.org",
            "extension": "2",
            "type": "Licite"
        },
        {
            "nom": "Open editions journal",
            "url": "journals.openedition.org",
            "extension": "2",
            "type": "Licite"
        },
        {
            "nom": "Opus",
            "url": "www.opus-foundation.org",
            "extension": "1",
            "type": "Licite"
        },
        {
            "nom": "Orange",
            "url": "jeu.orange.fr",
            "extension": "2",
            "type": "Licite"
        },
        {
            "nom": "Origin",
            "url": "www.origin.com/fr-fr/store",
            "extension": "2",
            "type": "Licite"
        },
        {
            "nom": "Outbuster",
            "url": "www.outbuster.com",
            "extension": "2",
            "type": "Licite"
        },
        {
            "nom": "Paradisio",
            "url": "www.contact@paradisopodcasts.com",
            "extension": "1",
            "type": "Licite"
        },
        {
            "nom": "Piwi+",
            "url": "www.piwiplus.fr",
            "extension": "2",
            "type": "Licite"
        },
        {
            "nom": "Pixabay",
            "url": "www.pixabay.com",
            "extension": "1",
            "type": "Licite"
        },
        {
            "nom": "Placedeslibraires.fr",
            "url": "www.placedeslibraires.fr",
            "extension": "2",
            "type": "Licite"
        },
        {
            "nom": "Planetr",
            "url": "www.planetr.fr",
            "extension": "2",
            "type": "Licite"
        },
        {
            "nom": "Playstation now",
            "url": "www.playstation.com/fr-fr/explore/playstation-now",
            "extension": "2",
            "type": "Licite"
        },
        {
            "nom": "PlayStation Store",
            "url": "www.sonyentertainmentnetwork.com/fr-fr/playstation-store",
            "extension": "2",
            "type": "Licite"
        },
        {
            "nom": "PlayUp",
            "url": "www.playup.fr",
            "extension": "2",
            "type": "Licite"
        },
        {
            "nom": "Playzer",
            "url": "www.playzer.fr/ ",
            "extension": "2",
            "type": "Licite"
        },
        {
            "nom": "Podcut",
            "url": "www.podcut.studio",
            "extension": "1",
            "type": "Licite"
        },
        {
            "nom": "Primephonic",
            "url": "www.primephonic.com",
            "extension": "2",
            "type": "Licite"
        },
        {
            "nom": "Project Gutenberg",
            "url": "www.gutenberg.org/browse/languages/fr",
            "extension": "2",
            "type": "Licite"
        },
        {
            "nom": "Public sénat",
            "url": "www.publicsenat.fr",
            "extension": "2",
            "type": "Licite"
        },
        {
            "nom": "Publie.net",
            "url": "www.publie.net",
            "extension": "2",
            "type": "Licite"
        },
        {
            "nom": "Publishroom",
            "url": "communaute.publishroom.com/?type=books",
            "extension": "2",
            "type": "Licite"
        },
        {
            "nom": "Qobuz",
            "url": "www.qobuz.com",
            "extension": "2",
            "type": "Licite"
        },
        {
            "nom": "Queer Screen",
            "url": "www.queerscreen.fr",
            "extension": "2",
            "type": "Licite"
        },
        {
            "nom": "Quibi",
            "url": "www.quibi.com",
            "extension": "1",
            "type": "Licite"
        },
        {
            "nom": "Quickpartitions",
            "url": "www.quickpartitions.com",
            "extension": "2",
            "type": "Licite"
        },
        {
            "nom": "Qwest TV",
            "url": "www.qwest.tv",
            "extension": "1",
            "type": "Licite"
        },
        {
            "nom": "Radioclassique",
            "url": "www.radioclassique.fr",
            "extension": "2",
            "type": "Licite"
        },
        {
            "nom": "RadioFrance",
            "url": "Application",
            "extension": "0",
            "type": "Licite"
        },
        {
            "nom": "RadioFrance",
            "url": "www.radiofrance.fr",
            "extension": "2",
            "type": "Licite"
        },
        {
            "nom": "RadioNova",
            "url": "www.nova.fr",
            "extension": "2",
            "type": "Licite"
        },
        {
            "nom": "Rakuten TV",
            "url": "fr.rakuten.tv",
            "extension": "2",
            "type": "Licite"
        },
        {
            "nom": "ReplayTV France",
            "url": "www.replay-tv-france.fr",
            "extension": "1",
            "type": "Licite"
        },
        {
            "nom": "RMC découverte",
            "url": "rmcdecouverte.bfmtv.com",
            "extension": "2",
            "type": "Licite"
        },
        {
            "nom": "RMC story",
            "url": "rmcstory.bfmtv.com",
            "extension": "2",
            "type": "Licite"
        },
        {
            "nom": "RTBF Radio",
            "url": "www.rtbf.be/radio",
            "extension": "2",
            "type": "Licite"
        },
        {
            "nom": "RTL2",
            "url": "www.6play.fr/rtl2",
            "extension": "2",
            "type": "Licite"
        },
        {
            "nom": "Ruedespromenades.com",
            "url": "www.ruedespromenades.com",
            "extension": "2",
            "type": "Licite"
        },
        {
            "nom": "Salto",
            "url": "www.salto.fr",
            "extension": "2",
            "type": "Licite"
        },
        {
            "nom": "Sauramps",
            "url": "sauramps.epagine.fr",
            "extension": "2",
            "type": "Licite"
        },
        {
            "nom": "Scenso.tv",
            "url": "www.scenso.tv",
            "extension": "2",
            "type": "Licite"
        },
        {
            "nom": "Scholar vox",
            "url": "www.scholarvox.com",
            "extension": "2",
            "type": "Licite"
        },
        {
            "nom": "Science et vie TV",
            "url": "www.science-et-vie.tv/live-replay.aspx",
            "extension": "3",
            "type": "Licite"
        },
        {
            "nom": "Scopalto",
            "url": "www.scopalto.com",
            "extension": "2",
            "type": "Licite"
        },
        {
            "nom": "Scope image",
            "url": "www.scope-image.com",
            "extension": "2",
            "type": "Licite"
        },
        {
            "nom": "Scribd",
            "url": "fr.scribd.com",
            "extension": "2",
            "type": "Licite"
        },
        {
            "nom": "Sequencity",
            "url": "www.sequencity.leclerc/fr-FR",
            "extension": "2",
            "type": "Licite"
        },
        {
            "nom": "SFR (jeu vidéo)",
            "url": "www.sfr.fr/jeux-video",
            "extension": "2",
            "type": "Licite"
        },
        {
            "nom": "SFR Play",
            "url": "www.sfr.fr/sfrplay",
            "extension": "2",
            "type": "Licite"
        },
        {
            "nom": "Shadowz",
            "url": "www.shadowz.fr",
            "extension": "2",
            "type": "Licite"
        },
        {
            "nom": "Sheet music direct",
            "url": "www.sheetmusicdirect.com/fr-FR",
            "extension": "2",
            "type": "Licite"
        },
        {
            "nom": "Short éditions",
            "url": "www.short-edition.com",
            "extension": "1",
            "type": "Licite"
        },
        {
            "nom": "Shorts TV",
            "url": "www.shorts.tv",
            "extension": "1",
            "type": "Licite"
        },
        {
            "nom": "Shutterstock",
            "url": "www.shutterstock.com",
            "extension": "2",
            "type": "Licite"
        },
        {
            "nom": "Skyrock",
            "url": "www.skyrock.com",
            "extension": "2",
            "type": "Licite"
        },
        {
            "nom": "Slash",
            "url": "www.france.tv/slash",
            "extension": "2",
            "type": "Licite"
        },
        {
            "nom": "Smartlibris",
            "url": "www.smartlibris.com",
            "extension": "2",
            "type": "Licite"
        },
        {
            "nom": "SNCF e-livre",
            "url": "e-livre.sncf.com",
            "extension": "2",
            "type": "Licite"
        },
        {
            "nom": "Soundcloud",
            "url": "www.soundcloud.com",
            "extension": "1",
            "type": "Licite"
        },
        {
            "nom": "Spamflix",
            "url": "spamflix.com/home.do",
            "extension": "2",
            "type": "Licite"
        },
        {
            "nom": "Spicee",
            "url": "www.spicee.com/fr/decouvrir",
            "extension": "2",
            "type": "Licite"
        },
        {
            "nom": "Spinlet",
            "url": "www.spinlet.com",
            "extension": "1",
            "type": "Licite"
        },
        {
            "nom": "Spotify",
            "url": "www.spotify.com/fr",
            "extension": "2",
            "type": "Licite"
        },
        {
            "nom": "Spotify Kids",
            "url": "www.spotify.com/fr/kids",
            "extension": "2",
            "type": "Licite"
        },
        {
            "nom": "Starzplay",
            "url": "www.starz.com/fr/fr",
            "extension": "2",
            "type": "Licite"
        },
        {
            "nom": "Steam",
            "url": "store.steampowered.com",
            "extension": "2",
            "type": "Licite"
        },
        {
            "nom": "Steam VR",
            "url": "store.steampowered.com/steamvr?l=french",
            "extension": "2",
            "type": "Licite"
        },
        {
            "nom": "Stitcher",
            "url": "www.stitcher.com",
            "extension": "2",
            "type": "Licite"
        },
        {
            "nom": "Storyplayr",
            "url": "www.storyplayr.com",
            "extension": "1",
            "type": "Licite"
        },
        {
            "nom": "Sybel",
            "url": "www.sybel.co/fr",
            "extension": "1",
            "type": "Licite"
        },
        {
            "nom": "Taleming",
            "url": "www.taleming.com",
            "extension": "1",
            "type": "Licite"
        },
        {
            "nom": "Teletoon+",
            "url": "www.teletoonplus.fr",
            "extension": "2",
            "type": "Licite"
        },
        {
            "nom": "Tënk",
            "url": "www.tenk.fr",
            "extension": "2",
            "type": "Licite"
        },
        {
            "nom": "TFOU Max",
            "url": "www.tfoumax.fr",
            "extension": "2",
            "type": "Licite"
        },
        {
            "nom": "TheBook Edition",
            "url": "www.thebookedition.com/fr",
            "extension": "2",
            "type": "Licite"
        },
        {
            "nom": "Tidal",
            "url": "www.tidal.com/fr",
            "extension": "1",
            "type": "Licite"
        },
        {
            "nom": "Tootak",
            "url": "www.tootak.fr",
            "extension": "2",
            "type": "Licite"
        },
        {
            "nom": "Toute l'histoire",
            "url": "www.toutelhistoire.com",
            "extension": "2",
            "type": "Licite"
        },
        {
            "nom": "Trace play",
            "url": "www.traceplay.tv/landing",
            "extension": "2",
            "type": "Licite"
        },
        {
            "nom": "Trek",
            "url": "www.trekhd.tv/live-replay.aspx",
            "extension": "3",
            "type": "Licite"
        },
        {
            "nom": "Tropismes librairies",
            "url": "tropismes.epagine.fr",
            "extension": "2",
            "type": "Licite"
        },
        {
            "nom": "TV5 Monde",
            "url": "www.tv5.org",
            "extension": "2",
            "type": "Licite"
        },
        {
            "nom": "TV5 Monde plus",
            "url": "www.tv5mondeplus.com",
            "extension": "2",
            "type": "Licite"
        },
        {
            "nom": "U-culture",
            "url": "www.uculture.fr/e-books.html",
            "extension": "3",
            "type": "Licite"
        },
        {
            "nom": "Universciné",
            "url": "www.universcine.com",
            "extension": "2",
            "type": "Licite"
        },
        {
            "nom": "UPblisher",
            "url": "www.upblisher.com",
            "extension": "2",
            "type": "Licite"
        },
        {
            "nom": "Uplay",
            "url": "uplay.ubi.com/fr-FR",
            "extension": "2",
            "type": "Licite"
        },
        {
            "nom": "Utomik",
            "url": "www.utomik.com",
            "extension": "2",
            "type": "Licite"
        },
        {
            "nom": "Vialma",
            "url": "www.vialma.com",
            "extension": "2",
            "type": "Licite"
        },
        {
            "nom": "Vidéo à la demande d'Orange",
            "url": "video-a-la-demande.orange.fr",
            "extension": "2",
            "type": "Licite"
        },
        {
            "nom": "VidéoClub Carlotta Films",
            "url": "levideoclub.carlottafilms.com",
            "extension": "2",
            "type": "Licite"
        },
        {
            "nom": "Viki",
            "url": "www.viki.com",
            "extension": "2",
            "type": "Licite"
        },
        {
            "nom": "Virgin Radio",
            "url": "www.virginradio.fr",
            "extension": "2",
            "type": "Licite"
        },
        {
            "nom": "Vivlio",
            "url": "www.vivlio.fr",
            "extension": "2",
            "type": "Licite"
        },
        {
            "nom": "VodMediathequenumerique",
            "url": "vod.mediatheque-numerique.com",
            "extension": "2",
            "type": "Licite"
        },
        {
            "nom": "Wakanim",
            "url": "www.wakanim.tv",
            "extension": "2",
            "type": "Licite"
        },
        {
            "nom": "Wallis photothèque",
            "url": "www.wallis.fr",
            "extension": "2",
            "type": "Licite"
        },
        {
            "nom": "Watch it !",
            "url": "www.watch-it.tv",
            "extension": "2",
            "type": "Licite"
        },
        {
            "nom": "Webtoon Factory",
            "url": "www.webtoonfactory.com/fr",
            "extension": "2",
            "type": "Licite"
        },
        {
            "nom": "Webtoons.com",
            "url": "www.webtoons.com",
            "extension": "2",
            "type": "Licite"
        },
        {
            "nom": "Wikisource",
            "url": "fr.wikisource.org/wiki/Accueil",
            "extension": "2",
            "type": "Licite"
        },
        {
            "nom": "Xbox Game Pass",
            "url": "www.xbox.com/fr-FR/xbox-game-pass",
            "extension": "2",
            "type": "Licite"
        },
        {
            "nom": "Youboox",
            "url": "www.youboox.fr",
            "extension": "1",
            "type": "Licite"
        },
        {
            "nom": "Youboox pop",
            "url": "www.youbooxpop.fr",
            "extension": "1",
            "type": "Licite"
        },
        {
            "nom": "Youscribe",
            "url": "www.youscribe.com",
            "extension": "2",
            "type": "Licite"
        },
        {
            "nom": "Youtube music",
            "url": "www.youtube.com/musicpremium",
            "extension": "2",
            "type": "Licite"
        },
        {
            "nom": "Youtube premium",
            "url": "www.youtube.com",
            "extension": "2",
            "type": "Licite"
        },
        {
            "nom": "Zphoto",
            "url": "www.zphoto.fr",
            "extension": "2",
            "type": "Licite"
        },
        {
            "nom": "Zylom",
            "url": "www.zylom.com/fr",
            "extension": "2",
            "type": "Licite"
        }
    ]
}